[
  {
    "id": 0
  },
  {
    "id": 1,
    "nombre": "matias",
    "apellido": "tolosa",
    "email": "matolox88@gmail.com",
    "password": "$2a$10$lUxp4yFmc1IlebAFojtipuA7eLfUNk36TqyY131RhrmoqtcGqZyMy",
    "nacimiento": "2020-02-15",
    "domicilio": "callao 2070",
    "avatar": "default.png"
  },
  {
    "id": 2,
    "nombre": "Franco ",
    "apellido": "Acosta",
    "email": "franco@o2admin",
    "password": "$2a$10$3cBnc6G85B.zymWPTBlz2..bpcfSncBOqzAyTfGMWYaR5AUbBuuli",
    "nacimiento": "1995-11-07",
    "domicilio": "Brandsen 805",
    "avatar": "default.png"
  },
  {
    "id": 3,
    "nombre": "prueba",
    "apellido": "prueba",
    "email": "prueba@prueba.com",
    "password": "$2a$10$WTQ/pirbZILHfCY75WiXC..3T53RReTI1bNaaa8.BlE5YoUWJLEmG",
    "nacimiento": "1995-11-07",
    "domicilio": "prueba",
    "avatar": "default.png"
  }
]